{"paths": {"admin/js/vendor/select2/i18n/af.js": "admin/js/vendor/select2/i18n/af.4f6fcd73488c.js", "admin/js/vendor/select2/i18n/ar.js": "admin/js/vendor/select2/i18n/ar.65aa8e36bf5d.js", "admin/js/vendor/select2/i18n/az.js": "admin/js/vendor/select2/i18n/az.270c257daf81.js", "admin/js/vendor/select2/i18n/bg.js": "admin/js/vendor/select2/i18n/bg.39b8be30d4f0.js", "admin/js/vendor/select2/i18n/bn.js": "admin/js/vendor/select2/i18n/bn.6d42b4dd5665.js", "admin/js/vendor/select2/i18n/bs.js": "admin/js/vendor/select2/i18n/bs.91624382358e.js", "admin/js/vendor/select2/i18n/ca.js": "admin/js/vendor/select2/i18n/ca.a166b745933a.js", "admin/js/vendor/select2/i18n/cs.js": "admin/js/vendor/select2/i18n/cs.4f43e8e7d33a.js", "admin/js/vendor/select2/i18n/da.js": "admin/js/vendor/select2/i18n/da.766346afe4dd.js", "admin/js/vendor/select2/i18n/de.js": "admin/js/vendor/select2/i18n/de.8a1c222b0204.js", "admin/js/vendor/select2/i18n/dsb.js": "admin/js/vendor/select2/i18n/dsb.56372c92d2f1.js", "admin/js/vendor/select2/i18n/el.js": "admin/js/vendor/select2/i18n/el.27097f071856.js", "admin/js/vendor/select2/i18n/en.js": "admin/js/vendor/select2/i18n/en.cf932ba09a98.js", "admin/js/vendor/select2/i18n/es.js": "admin/js/vendor/select2/i18n/es.66dbc2652fb1.js", "admin/js/vendor/select2/i18n/et.js": "admin/js/vendor/select2/i18n/et.2b96fd98289d.js", "admin/js/vendor/select2/i18n/eu.js": "admin/js/vendor/select2/i18n/eu.adfe5c97b72c.js", "admin/js/vendor/select2/i18n/fa.js": "admin/js/vendor/select2/i18n/fa.3b5bd1961cfd.js", "admin/js/vendor/select2/i18n/fi.js": "admin/js/vendor/select2/i18n/fi.614ec42aa9ba.js", "admin/js/vendor/select2/i18n/fr.js": "admin/js/vendor/select2/i18n/fr.05e0542fcfe6.js", "admin/js/vendor/select2/i18n/gl.js": "admin/js/vendor/select2/i18n/gl.d99b1fedaa86.js", "admin/js/vendor/select2/i18n/he.js": "admin/js/vendor/select2/i18n/he.e420ff6cd3ed.js", "admin/js/vendor/select2/i18n/hi.js": "admin/js/vendor/select2/i18n/hi.70640d41628f.js", "admin/js/vendor/select2/i18n/hr.js": "admin/js/vendor/select2/i18n/hr.a2b092cc1147.js", "admin/js/vendor/select2/i18n/hsb.js": "admin/js/vendor/select2/i18n/hsb.fa3b55265efe.js", "admin/js/vendor/select2/i18n/hu.js": "admin/js/vendor/select2/i18n/hu.6ec6039cb8a3.js", "admin/js/vendor/select2/i18n/hy.js": "admin/js/vendor/select2/i18n/hy.c7babaeef5a6.js", "admin/js/vendor/select2/i18n/id.js": "admin/js/vendor/select2/i18n/id.04debded514d.js", "admin/js/vendor/select2/i18n/is.js": "admin/js/vendor/select2/i18n/is.3ddd9a6a97e9.js", "admin/js/vendor/select2/i18n/it.js": "admin/js/vendor/select2/i18n/it.be4fe8d365b5.js", "admin/js/vendor/select2/i18n/ja.js": "admin/js/vendor/select2/i18n/ja.170ae885d74f.js", "admin/js/vendor/select2/i18n/ka.js": "admin/js/vendor/select2/i18n/ka.2083264a54f0.js", "admin/js/vendor/select2/i18n/km.js": "admin/js/vendor/select2/i18n/km.c23089cb06ca.js", "admin/js/vendor/select2/i18n/ko.js": "admin/js/vendor/select2/i18n/ko.e7be6c20e673.js", "admin/js/vendor/select2/i18n/lt.js": "admin/js/vendor/select2/i18n/lt.23c7ce903300.js", "admin/js/vendor/select2/i18n/lv.js": "admin/js/vendor/select2/i18n/lv.08e62128eac1.js", "admin/js/vendor/select2/i18n/mk.js": "admin/js/vendor/select2/i18n/mk.dabbb9087130.js", "admin/js/vendor/select2/i18n/ms.js": "admin/js/vendor/select2/i18n/ms.4ba82c9a51ce.js", "admin/js/vendor/select2/i18n/nb.js": "admin/js/vendor/select2/i18n/nb.da2fce143f27.js", "admin/js/vendor/select2/i18n/ne.js": "admin/js/vendor/select2/i18n/ne.3d79fd3f08db.js", "admin/js/vendor/select2/i18n/nl.js": "admin/js/vendor/select2/i18n/nl.997868a37ed8.js", "admin/js/vendor/select2/i18n/pl.js": "admin/js/vendor/select2/i18n/pl.6031b4f16452.js", "admin/js/vendor/select2/i18n/ps.js": "admin/js/vendor/select2/i18n/ps.38dfa47af9e0.js", "admin/js/vendor/select2/i18n/pt-BR.js": "admin/js/vendor/select2/i18n/pt-BR.e1b294433e7f.js", "admin/js/vendor/select2/i18n/pt.js": "admin/js/vendor/select2/i18n/pt.33b4a3b44d43.js", "admin/js/vendor/select2/i18n/ro.js": "admin/js/vendor/select2/i18n/ro.f75cb460ec3b.js", "admin/js/vendor/select2/i18n/ru.js": "admin/js/vendor/select2/i18n/ru.934aa95f5b5f.js", "admin/js/vendor/select2/i18n/sk.js": "admin/js/vendor/select2/i18n/sk.33d02cef8d11.js", "admin/js/vendor/select2/i18n/sl.js": "admin/js/vendor/select2/i18n/sl.131a78bc0752.js", "admin/js/vendor/select2/i18n/sq.js": "admin/js/vendor/select2/i18n/sq.5636b60d29c9.js", "admin/js/vendor/select2/i18n/sr-Cyrl.js": "admin/js/vendor/select2/i18n/sr-Cyrl.f254bb8c4c7c.js", "admin/js/vendor/select2/i18n/sr.js": "admin/js/vendor/select2/i18n/sr.5ed85a48f483.js", "admin/js/vendor/select2/i18n/sv.js": "admin/js/vendor/select2/i18n/sv.7a9c2f71e777.js", "admin/js/vendor/select2/i18n/th.js": "admin/js/vendor/select2/i18n/th.f38c20b0221b.js", "admin/js/vendor/select2/i18n/tk.js": "admin/js/vendor/select2/i18n/tk.7c572a68c78f.js", "admin/js/vendor/select2/i18n/tr.js": "admin/js/vendor/select2/i18n/tr.b5a0643d1545.js", "admin/js/vendor/select2/i18n/uk.js": "admin/js/vendor/select2/i18n/uk.8cede7f4803c.js", "admin/js/vendor/select2/i18n/vi.js": "admin/js/vendor/select2/i18n/vi.097a5b75b3e1.js", "admin/js/vendor/select2/i18n/zh-CN.js": "admin/js/vendor/select2/i18n/zh-CN.2cff662ec5f9.js", "admin/js/vendor/select2/i18n/zh-TW.js": "admin/js/vendor/select2/i18n/zh-TW.04554a227c2b.js", "admin/css/vendor/select2/LICENSE-SELECT2.md": "admin\\css\\vendor\\select2\\LICENSE-SELECT2.f94142512c91.md", "admin/css/vendor/select2/select2.css": "admin/css/vendor/select2/select2.a2194c262648.css", "admin/css/vendor/select2/select2.min.css": "admin/css/vendor/select2/select2.min.9f54e6414f87.css", "admin/js/vendor/jquery/jquery.js": "admin/js/vendor/jquery/jquery.0208b96062ba.js", "admin/js/vendor/jquery/jquery.min.js": "admin/js/vendor/jquery/jquery.min.641dd1437010.js", "admin/js/vendor/jquery/LICENSE.txt": "admin\\js\\vendor\\jquery\\LICENSE.de877aa6d744.txt", "admin/js/vendor/select2/LICENSE.md": "admin\\js\\vendor\\select2\\LICENSE.f94142512c91.md", "admin/js/vendor/select2/select2.full.js": "admin/js/vendor/select2/select2.full.c2afdeda3058.js", "admin/js/vendor/select2/select2.full.min.js": "admin/js/vendor/select2/select2.full.min.fcd7500d8e13.js", "admin/js/vendor/xregexp/LICENSE.txt": "admin\\js\\vendor\\xregexp\\LICENSE.bf79e414957a.txt", "admin/js/vendor/xregexp/xregexp.js": "admin/js/vendor/xregexp/xregexp.efda034b9537.js", "admin/js/vendor/xregexp/xregexp.min.js": "admin/js/vendor/xregexp/xregexp.min.b0439563a5d3.js", "admin/img/gis/move_vertex_off.svg": "admin\\img\\gis\\move_vertex_off.7a23bf31ef8a.svg", "admin/img/gis/move_vertex_on.svg": "admin\\img\\gis\\move_vertex_on.0047eba25b67.svg", "admin/js/admin/DateTimeShortcuts.js": "admin/js/admin/DateTimeShortcuts.9f6e209cebca.js", "admin/js/admin/RelatedObjectLookups.js": "admin/js/admin/RelatedObjectLookups.8609f99b9ab2.js", "admin/css/autocomplete.css": "admin/css/autocomplete.4a81fc4242d0.css", "admin/css/base.css": "admin/css/base.64976e0f7339.css", "admin/css/changelists.css": "admin/css/changelists.9237a1ac391b.css", "admin/css/dark_mode.css": "admin/css/dark_mode.ef27a31af300.css", "admin/css/dashboard.css": "admin/css/dashboard.e90f2068217b.css", "admin/css/forms.css": "admin/css/forms.3b181cba6653.css", "admin/css/login.css": "admin/css/login.586129c60a93.css", "admin/css/nav_sidebar.css": "admin/css/nav_sidebar.269a1bd44627.css", "admin/css/responsive.css": "admin/css/responsive.107cd2690311.css", "admin/css/responsive_rtl.css": "admin/css/responsive_rtl.97b066429fd8.css", "admin/css/rtl.css": "admin/css/rtl.4685390ad96d.css", "admin/css/widgets.css": "admin/css/widgets.0a3765e806b3.css", "admin/img/calendar-icons.svg": "admin\\img\\calendar-icons.39b290681a8b.svg", "admin/img/icon-addlink.svg": "admin\\img\\icon-addlink.d519b3bab011.svg", "admin/img/icon-alert.svg": "admin\\img\\icon-alert.034cc7d8a67f.svg", "admin/img/icon-calendar.svg": "admin\\img\\icon-calendar.ac7aea671bea.svg", "admin/img/icon-changelink.svg": "admin\\img\\icon-changelink.18d2fd706348.svg", "admin/img/icon-clock.svg": "admin\\img\\icon-clock.e1d4dfac3f2b.svg", "admin/img/icon-deletelink.svg": "admin\\img\\icon-deletelink.564ef9dc3854.svg", "admin/img/icon-no.svg": "admin\\img\\icon-no.439e821418cd.svg", "admin/img/icon-unknown-alt.svg": "admin\\img\\icon-unknown-alt.81536e128bb6.svg", "admin/img/icon-unknown.svg": "admin\\img\\icon-unknown.a18cb4398978.svg", "admin/img/icon-viewlink.svg": "admin\\img\\icon-viewlink.41eb31f7826e.svg", "admin/img/icon-yes.svg": "admin\\img\\icon-yes.d2f9f035226a.svg", "admin/img/inline-delete.svg": "admin\\img\\inline-delete.fec1b761f254.svg", "admin/img/LICENSE": "admin\\img\\LICENSE.2c54f4e1ca1c", "admin/img/README.txt": "admin\\img\\README.a70711a38d87.txt", "admin/img/search.svg": "admin\\img\\search.7cf54ff789c6.svg", "admin/img/selector-icons.svg": "admin\\img\\selector-icons.b4555096cea2.svg", "admin/img/sorting-icons.svg": "admin\\img\\sorting-icons.3a097b59f104.svg", "admin/img/tooltag-add.svg": "admin\\img\\tooltag-add.e59d620a9742.svg", "admin/img/tooltag-arrowright.svg": "admin\\img\\tooltag-arrowright.bbfb788a849e.svg", "admin/js/actions.js": "admin/js/actions.eac7e3441574.js", "admin/js/autocomplete.js": "admin/js/autocomplete.01591ab27be7.js", "admin/js/calendar.js": "admin/js/calendar.f8a5d055eb33.js", "admin/js/cancel.js": "admin/js/cancel.ecc4c5ca7b32.js", "admin/js/change_form.js": "admin/js/change_form.9d8ca4f96b75.js", "admin/js/collapse.js": "admin/js/collapse.f84e7410290f.js", "admin/js/core.js": "admin/js/core.cf103cd04ebf.js", "admin/js/filters.js": "admin/js/filters.0e360b7a9f80.js", "admin/js/inlines.js": "admin/js/inlines.22d4d93c00b4.js", "admin/js/jquery.init.js": "admin/js/jquery.init.b7781a0897fc.js", "admin/js/nav_sidebar.js": "admin/js/nav_sidebar.3b9190d420b1.js", "admin/js/popup_response.js": "admin/js/popup_response.c6cc78ea5551.js", "admin/js/prepopulate.js": "admin/js/prepopulate.bd2361dfd64d.js", "admin/js/prepopulate_init.js": "admin/js/prepopulate_init.6cac7f3105b8.js", "admin/js/SelectBox.js": "admin/js/SelectBox.7d3ce5a98007.js", "admin/js/SelectFilter2.js": "admin/js/SelectFilter2.bdb8d0cc579e.js", "admin/js/theme.js": "admin/js/theme.ab270f56bb9c.js", "admin/js/urlify.js": "admin/js/urlify.ae970a820212.js", "images/about.txt": "images\\about.5efb929d72a3.txt", "images/android-chrome-192x192.png": "images\\android-chrome-192x192.1fb1b1f446d1.png", "images/android-chrome-512x512.png": "images\\android-chrome-512x512.fa2ec49fa0e7.png", "images/apple-touch-icon.png": "images\\apple-touch-icon.4de314cdc626.png", "images/favicon-16x16.png": "images\\favicon-16x16.54a3cd1dbe5c.png", "images/favicon-32x32.png": "images\\favicon-32x32.1a565e04fdea.png", "images/favicon.ico": "images\\favicon.e0dc71c9f50a.ico", "images/site.webmanifest": "images\\site.053100cb84a5.webmanifest", "img/android-chrome-192x192.png": "img/android-chrome-192x192.a7b072c84809.png", "img/android-chrome-512x512.png": "img/android-chrome-512x512.ad5eb168b996.png", "img/apple-touch-icon.png": "img/apple-touch-icon.b49ee8042c13.png", "img/favicon-16x16.png": "img/favicon-16x16.099d151a509b.png", "img/favicon-32x32.png": "img/favicon-32x32.13b6553239e0.png", "img/favicon.ico": "img/favicon.7430454e8a82.ico", "img/site.webmanifest": "img/site.053100cb84a5.webmanifest", "img2/android-chrome-192x192.png": "img2/android-chrome-192x192.d1ccdbf405c2.png", "img2/android-chrome-512x512.png": "img2/android-chrome-512x512.2d8b56458eec.png", "img2/apple-touch-icon.png": "img2/apple-touch-icon.36386eb5aec6.png", "img2/favicon-16x16.png": "img2/favicon-16x16.9097e819391c.png", "img2/favicon-32x32.png": "img2/favicon-32x32.38b888d2aa70.png", "img2/favicon.ico": "img2/favicon.6811ae822771.ico", "img2/site.webmanifest": "img2/site.053100cb84a5.webmanifest", "02.jpg": "02.4a89fa3ff998.jpg", "1-removebg-preview.png": "1-removebg-preview.4f6fc5544ed2.png", "1209457_9634-removebg-preview.png": "1209457_9634-removebg-preview.eb76f04a8512.png", "1617955368-Clara Kathi WillburnWhatsApp Image 2021-04-09 at 8.59.37 AM.jpg": "1617955368-Clara Kathi WillburnWhatsApp Image 2021-04-09 at 8.59.37 AM.231743fd0ecd.jpg", "1617955468-Denise Fletcher WhatsApp Image 2021-01-16 at 1.36.21 PM.jpg": "1617955468-Denise Fletcher WhatsApp Image 2021-01-16 at 1.36.21 PM.3dd949826ecf.jpg", "1617956107-Jeffery KumarWhatsApp Image 2021-04-09 at 9.13.44 AM.jpg": "1617956107-Jeffery KumarWhatsApp Image 2021-04-09 at 9.13.44 AM.080d21494201.jpg", "19198921.jpg": "19198921.bebbf0e70e8d.jpg", "2-removebg-preview.png": "2-removebg-preview.a2401d5cfb56.png", "21250116_6424090-removebg-preview.png": "21250116_6424090-removebg-preview.8f2261a17a54.png", "30-removebg-preview.png": "30-removebg-preview.9ea31486a273.png", "31756147_2203.i201.078.F.m004.c9.web_3_technology_isometirc-removebg-preview.png": "31756147_2203.i201.078.F.m004.c9.web_3_technology_isometirc-removebg-preview.bf2f2e92e255.png", "3188-removebg-preview.png": "3188-removebg-preview.debfdf6639f9.png", "4-2-success-png.png": "4-2-success-png.7dc87830bead.png", "4791198_49242-removebg-preview.png": "4791198_49242-removebg-preview.699e4b88996c.png", "6208882-removebg-preview.png": "6208882-removebg-preview.eb555af03905.png", "6345978_24963-removebg-preview.png": "6345978_24963-removebg-preview.4f02250a37b4.png", "67-671931_time-png-transparent-png-removebg-preview.png": "67-671931_time-png-transparent-png-removebg-preview.1ecd1667b52a.png", "67-671931_time-png-transparent-png.png": "67-671931_time-png-transparent-png.d7d311a56912.png", "7181.png_1200-removebg-preview.png": "7181.png_1200-removebg-preview.f5d968216b60.png", "7181.png_1200.png": "7181.png_1200.e70ada252c15.png", "about_laptop.jpg": "about_laptop.7d51a03ca791.jpg", "about_laptop.png": "about_laptop.c5b33da2adfa.png", "bitcoin-img.png": "bitcoin-img.b1ca0f40dd25.png", "Digital_World__1_-removebg-preview.png": "Digital_World__1_-removebg-preview.4a5563969e61.png", "download (1).jpeg": "download (1).62b5596ff1d9.jpeg", "expertise2.jpg": "expertise2.b846abc87657.jpg", "expertise3.jpg": "expertise3.91119c8713f7.jpg", "happy-young-woman-talking-cell-phone-against-green-background_23-2148056310.avif": "happy-young-woman-talking-cell-phone-against-green-background_23-2148056310.b49c5f79c0d9.avif", "icons8-banknotes-48.png": "icons8-banknotes-48.60402284acab.png", "icons8-bitcoin-50.png": "icons8-bitcoin-50.206fe9c03f26.png", "icons8-coins-48.png": "icons8-coins-48.888f7d7d4548.png", "icons8-dollar-50.png": "icons8-dollar-50.c4f0188ad4ce.png", "icons8-dollar-coin-50.png": "icons8-dollar-coin-50.58637e8d5e12.png", "icons8-dollars-64.png": "icons8-dollars-64.6f758cbb8971.png", "icons8-history-50.png": "icons8-history-50.eb5eab860da2.png", "icons8-money-bag-48.png": "icons8-money-bag-48.f62680d42efe.png", "icons8-money-bag-50.png": "icons8-money-bag-50.0df171ac1820.png", "icons8-money-transfer-48.png": "icons8-money-transfer-48.93c7e948f26c.png", "icons8-profile-picture-64.png": "icons8-profile-picture-64.b0a8aa3b6977.png", "icons8-settings-50.png": "icons8-settings-50.43cad5f97085.png", "icons8-stall-50.png": "icons8-stall-50.60b9530cb284.png", "icons8-transaction-50.png": "icons8-transaction-50.772d47103f6d.png", "icons8-wallet-50.png": "icons8-wallet-50.2ae1b32453ee.png", "Mar-Business_18.eps": "Mar-Business_18.f6065a078bd1.eps", "Mar-Business_18.jpg": "Mar-Business_18.cb841b93b11c.jpg", "onboarding.css": "onboarding.ed3a9c167230.css", "onboarding.js": "onboarding.0a47bad36054.js", "pensive-curly-haired-female-student-calls-groupmate-via-smartphone-sits-chair-own-study-room-table-with-desk-lamp-notepads-sticky-notes-wall-with-written-information.jpg": "pensive-curly-haired-female-student-calls-groupmate-via-smartphone-sits-chair-own-study-room-table-with-desk-lamp-notepads-sticky-notes-wall-with-written-information.d1119fede107.jpg", "png-clipart-time-management-time-attendance-clocks-time-and-attendance-others-time-entrepreneurship-thumbnail-removebg-preview.png": "png-clipart-time-management-time-attendance-clocks-time-and-attendance-others-time-entrepreneurship-thumbnail-removebg-preview.ec3690bd53f9.png", "png-clipart-time-management-time-attendance-clocks-time-and-attendance-others-time-entrepreneurship-thumbnail.png": "png-clipart-time-management-time-attendance-clocks-time-and-attendance-others-time-entrepreneurship-thumbnail.24f7f9dc8604.png", "slider-2.png": "slider-2.a19a75995ed7.png", "testimonial_img.jpg": "testimonial_img.2c498df74c1b.jpg", "testimonial_img2.jpg": "testimonial_img2.d7cfa5556608.jpg", "time-animation_1.gif": "time-animation_1.118fe5be7a5e.gif"}, "version": "1.1", "hash": "4c8901bffa9d"}